README.rst
setup.cfg
setup.py
collective/__init__.py
collective.publications.egg-info/PKG-INFO
collective.publications.egg-info/SOURCES.txt
collective.publications.egg-info/dependency_links.txt
collective.publications.egg-info/entry_points.txt
collective.publications.egg-info/namespace_packages.txt
collective.publications.egg-info/not-zip-safe
collective.publications.egg-info/paster_plugins.txt
collective.publications.egg-info/requires.txt
collective.publications.egg-info/top_level.txt
collective/publications/__init__.py
collective/publications/setuphandlers.py
collective/publications/tests.py
collective/publications/browser/__init__.py
collective/publications/browser/conversation.py
collective/publications/content/__init__.py
collective/publications/content/catalog.py
collective/publications/content/publication.py
collective/publications/upgrades/__init__.py
collective/publications/upgrades/upgrades.py