Metadata-Version: 1.1
Name: collective.publications
Version: 0.2
Summary: Provides a publication content type based on dexterity
Home-page: https://github.com/numahell/collective.publications/
Author: Emmanuelle HELLY
Author-email: emmanuelle.helly@makina-corpus.net
License: GPL
Keywords: plone content publications dexterity
Platform: UNKNOWN
Classifier: Framework :: Plone
Classifier: Programming Language :: Python
Classifier: Topic :: Software Development :: Libraries :: Python Modules
Classifier: License :: OSI Approved :: GNU General Public License (GPL)
